pangsitpy/__init__.py
pangsitpy/audio_extraction.py
pangsitpy/audio_processing.py
pangsitpy/audio_to_image.py
pangsitpy/audio_to_text.py
pangsitpy/cnn.py
pangsitpy/confusion_matrix.py
pangsitpy/image_extraction.py
pangsitpy/image_processing.py
pangsitpy/model.py
pangsitpy/scaling.py
pangsitpy/text_processing.py
pangsitpy/text_tokenizer.py
pangsitpy-0.0.14.dist-info/LICENSE
pangsitpy-0.0.14.dist-info/METADATA
pangsitpy-0.0.14.dist-info/WHEEL
pangsitpy-0.0.14.dist-info/top_level.txt
pangsitpy-0.0.14.dist-info/RECORD
